README.txt
setup.cfg
setup.py
Products/__init__.py
Products.CMFNotification.egg-info/PKG-INFO
Products.CMFNotification.egg-info/SOURCES.txt
Products.CMFNotification.egg-info/dependency_links.txt
Products.CMFNotification.egg-info/entry_points.txt
Products.CMFNotification.egg-info/namespace_packages.txt
Products.CMFNotification.egg-info/not-zip-safe
Products.CMFNotification.egg-info/requires.txt
Products.CMFNotification.egg-info/top_level.txt
Products/CMFNotification/LICENSE.txt
Products/CMFNotification/NotificationTool.py
Products/CMFNotification/README.txt
Products/CMFNotification/__init__.py
Products/CMFNotification/config.py
Products/CMFNotification/configure.zcml
Products/CMFNotification/exceptions.py
Products/CMFNotification/exportimport.py
Products/CMFNotification/patches.py
Products/CMFNotification/permissions.py
Products/CMFNotification/tool.gif
Products/CMFNotification/utils.py
Products/CMFNotification/version.txt
Products/CMFNotification/Extensions/Install.py
Products/CMFNotification/Extensions/__init__.py
Products/CMFNotification/browser/__init__.py
Products/CMFNotification/browser/configure.zcml
Products/CMFNotification/browser/portlet.py
Products/CMFNotification/browser/subscription.py
Products/CMFNotification/browser/resources/cmfnotification.kss
Products/CMFNotification/browser/templates/portlet.pt
Products/CMFNotification/doc/developer-notes.txt
Products/CMFNotification/doc/future.txt
Products/CMFNotification/doc/how-to-notify-a-group.txt
Products/CMFNotification/doc/how-to-setup-in-2-minutes.txt
Products/CMFNotification/doc/how-to-troubleshoot.txt
Products/CMFNotification/doc/index.txt
Products/CMFNotification/doc/install.txt
Products/CMFNotification/doc/rules-reference.txt
Products/CMFNotification/events/__init__.py
Products/CMFNotification/events/events.txt
Products/CMFNotification/events/events.zcml
Products/CMFNotification/events/handlers.py
Products/CMFNotification/i18n/cmfnotification-ca.po
Products/CMFNotification/i18n/cmfnotification-de.po
Products/CMFNotification/i18n/cmfnotification-es.po
Products/CMFNotification/i18n/cmfnotification-fr.po
Products/CMFNotification/i18n/cmfnotification-pt-br.po
Products/CMFNotification/i18n/cmfnotification.pot
Products/CMFNotification/i18n/plone-ca.po
Products/CMFNotification/i18n/plone-en.po
Products/CMFNotification/i18n/plone-es.po
Products/CMFNotification/i18n/plone-fr.po
