Metadata-Version: 1.0
Name: Products.CMFNotification
Version: 2.2
Summary: CMFNotification is a Plone product that allows users to be notified
Home-page: http://plone.org/products/cmfnotification
Author: Pilot Systems
Author-email: ploneorg@pilotsystems.net
License: GPL
Keywords: CMFNotification plone notification e-mail
Platform: UNKNOWN
Classifier: Framework :: Plone
Classifier: Programming Language :: Python
Classifier: Development Status :: 5 - Production/Stable
